LICENSE.txt
README.md
setup.cfg
setup.py
aether_grpc/__init__.py
aether_grpc.egg-info/PKG-INFO
aether_grpc.egg-info/SOURCES.txt
aether_grpc.egg-info/dependency_links.txt
aether_grpc.egg-info/requires.txt
aether_grpc.egg-info/top_level.txt
aether_grpc/services/__init__.py
aether_grpc/services/api_service_pb2.py
aether_grpc/services/api_service_pb2_grpc.py