Metadata-Version: 2.1
Name: aether-grpc
Version: 1.2.2
Summary: Aether GRPC definitions
Home-page: https://github.com/aether-labs/aether-grpc
Author: Calum Webb
Author-email: calumpeterwebb@icloud.com
License: UNKNOWN
Download-URL: https://github.com/aether-labs/aether-grpc/archive/refs/tags/1.2.2.tar.gz
Keywords: aether,aether-grpc,grpc
Platform: UNKNOWN
Classifier: Development Status :: 3 - Alpha
Classifier: Intended Audience :: Developers
Classifier: Topic :: Software Development :: Build Tools
Classifier: License :: OSI Approved :: MIT License
Classifier: Programming Language :: Python :: 3.8
Provides-Extra: dev
